{
  "platform": "facebook",
  "post_url": "https://www.facebook.com/reel/946304741296396",
  "posted_at": "2026-02-16",
  "campaign_slug": "2026-02-16-hod-only14-percent-tt-video",
  "asset_type": "video",
  "boosted": false,
  "notionsocial": {
    "source": "notionsocial",
    "synced_at": "2026-02-22",
    "views": 2491,
    "likes": 22,
    "comments": 2,
    "shares": 0
  },
  "platform_api": {
    "source": "facebook_api",
    "synced_at": "",
    "impressions": 0,
    "reach": 0,
    "likes": 0,
    "comments": 0,
    "shares": 0,
    "engagement_rate": 0
  },
  "notes": "Auto-created from Notion sync. Notionsocial metrics are surface-level. Platform API metrics populate when API integration is connected."
}
