{
  "platform": "LinkedIn",
  "post_url": "",
  "posted_at": "",
  "campaign_slug": "",
  "asset_type": "video-longform",
  "boosted": false,
  "sponsored_dates": {
    "start": "",
    "end": ""
  },
  "impressions": 0,
  "reach": 0,
  "views": 0,
  "watch_time_hours": 0.6947222222222222,
  "avg_view_duration_seconds": 10,
  "clicks": 0,
  "ctr": 0,
  "reactions": 0,
  "comments": 0,
  "reposts": 0,
  "follows": 0,
  "leads": 0,
  "engagements": 0,
  "engagement_rate": 0,
  "organic": {
    "impressions": 684,
    "reach": 338,
    "engagements": 30,
    "engagement_rate": 4.4,
    "clicks": 25,
    "click_through_rate": 3.7,
    "reactions": 4,
    "comments": 0,
    "reposts": 1,
    "page_viewers": 0,
    "followers_gained": 0,
    "video_views": 232,
    "watch_time_total": "41m 41s",
    "average_watch_time_seconds": 10
  },
  "sponsored": {
    "impressions": 0,
    "engagements": 0,
    "engagement_rate": 0,
    "clicks": 0,
    "click_through_rate": 0,
    "reactions": 0,
    "comments": 0,
    "reposts": 0,
    "video_views": 0,
    "ecpm": 0,
    "cost_per_engagement": 0,
    "spend": 0
  },
  "notes": ""
}